com/phida/main/Maintenance.py
com/phida/main/Operations.py
com/phida/main/PartitionAnalyzer.py
com/phida/main/PerfAnalyzer.py
com/phida/main/SilverMerge.py
com/phida/main/WorkflowBuilder.py
com/phida/main/__init__.py
com/phida/main/logging.py
com/phida/main/profileConfig.py
com/phida/main/profileVars.py
com/phida/main/sparksession.py
com/phida/main/utils.py
com/phida/main/utilsDatabricksAPI.py
com/phida/main/bronze/BronzeAppend.py
com/phida/main/bronze/WorkflowBuilder.py
com/phida/main/bronze/__init__.py
com/phida/tests/OperationsTest.py
com/phida/tests/__init__.py
com/phida/tests/conftest.py
com/phida/tests/test_Operations.py
com/phida/tests/test_utils.py
SilverStreamingApplicationWindchill-1.6.dist-info/METADATA
SilverStreamingApplicationWindchill-1.6.dist-info/WHEEL
SilverStreamingApplicationWindchill-1.6.dist-info/top_level.txt
SilverStreamingApplicationWindchill-1.6.dist-info/RECORD
