Metadata-Version: 2.1
Name: SilverStreamingApplicationWindchill
Version: 1.6
Summary: bronze append logic added
Home-page: 
Author: 
Author-email: 
License: UNKNOWN
Platform: UNKNOWN
